dvarpal/__init__.py
dvarpal/config.py
dvarpal/session.py
dvarpal/session_firefox.py
dvarpal-2.0.1.dist-info/METADATA
dvarpal-2.0.1.dist-info/WHEEL
dvarpal-2.0.1.dist-info/top_level.txt
dvarpal-2.0.1.dist-info/RECORD
