Metadata-Version: 2.1
Name: dvarpal
Version: 2.0.1
Summary: Automated broker login and token generator using Firefox ESR and Selenium
Home-page: https://github.com/sharmaak/dvarpal
Author: Amit Kumar Sharma
Author-email: amit.official@gmail.com
Classifier: Development Status :: 4 - Beta
Classifier: Intended Audience :: Developers
Classifier: License :: OSI Approved :: MIT License
Classifier: Programming Language :: Python :: 3
Classifier: Operating System :: POSIX :: Linux
Requires-Python: >=3.8
Requires-Dist: PyYAML~=6.0.2
Requires-Dist: requests
Requires-Dist: pyotp
Requires-Dist: upstox-python-sdk
Requires-Dist: undetected-chromedriver
Requires-Dist: selenium
